antidox/__init__.py
antidox/collector.py
antidox/directives.py
antidox/doxy.py
antidox/nodes.py
antidox/shell.py
antidox/xtransform.py
antidox/templates/compound.xsl
antidox-0.1.3.dist-info/LICENSE
antidox-0.1.3.dist-info/METADATA
antidox-0.1.3.dist-info/WHEEL
antidox-0.1.3.dist-info/entry_points.txt
antidox-0.1.3.dist-info/top_level.txt
antidox-0.1.3.dist-info/zip-safe
antidox-0.1.3.dist-info/RECORD
