Metadata-Version: 2.1
Name: antidox
Version: 0.1.3
Summary: Sphinx extension to extract and insert Doxygen documentation.
Home-page: https://github.com/jcarrano/antidox
Author: Juan I Carrano <juan@carrano.com.ar>
Author-email: juan@carrano.com.ar
License: BSD
Project-URL: Documentation, https://antidox.readthedocs.io/en/latest/index.html
Project-URL: Tracker, https://github.com/jcarrano/antidox/issues
Keywords: sphinx doxygen
Platform: UNKNOWN
Classifier: Development Status :: 4 - Beta
Classifier: License :: OSI Approved :: BSD License
Classifier: Programming Language :: Python :: 3
Classifier: Intended Audience :: Developers
Classifier: Framework :: Sphinx :: Extension
Classifier: Topic :: Documentation :: Sphinx
Classifier: Topic :: Software Development :: Documentation
Requires-Dist: sphinx
Requires-Dist: lxml
